img_cache/__init__.py
img_cache/core.py
img_cache/func.py
img_cache/sample.py
img_cache/types.py
img_cache-0.2.0.dist-info/METADATA
img_cache-0.2.0.dist-info/WHEEL
img_cache-0.2.0.dist-info/top_level.txt
img_cache-0.2.0.dist-info/RECORD
