Metadata-Version: 2.1
Name: img_cache
Version: 0.2.0
Author-email: svtter <svtter@qq.com>, svtter <svtter@163.com>
License: BSD
Requires-Python: <4.0,>=3.9
